meta_mcp/__init__.py
meta_mcp-0.0.1.dist-info/METADATA
meta_mcp-0.0.1.dist-info/WHEEL
meta_mcp-0.0.1.dist-info/top_level.txt
meta_mcp-0.0.1.dist-info/RECORD
