Metadata-Version: 2.4
Name: meta-mcp
Version: 0.0.1
Summary: Coming soon
Author-email: Your Name <you@example.com>
License: MIT
Requires-Python: >=3.7
